odoo8_addon_l10n_fr_intrastat_service-8.0.2.0.0.99.dev25-py3.8-nspkg.pth
odoo_addons/l10n_fr_intrastat_service/README.rst
odoo_addons/l10n_fr_intrastat_service/__init__.py
odoo_addons/l10n_fr_intrastat_service/__openerp__.py
odoo_addons/l10n_fr_intrastat_service/intrastat_demo.xml
odoo_addons/l10n_fr_intrastat_service/intrastat_service.py
odoo_addons/l10n_fr_intrastat_service/intrastat_service_reminder.xml
odoo_addons/l10n_fr_intrastat_service/intrastat_service_view.xml
odoo_addons/l10n_fr_intrastat_service/data/des.xsd
odoo_addons/l10n_fr_intrastat_service/i18n/am.po
odoo_addons/l10n_fr_intrastat_service/i18n/ar.po
odoo_addons/l10n_fr_intrastat_service/i18n/bg.po
odoo_addons/l10n_fr_intrastat_service/i18n/bs.po
odoo_addons/l10n_fr_intrastat_service/i18n/ca.po
odoo_addons/l10n_fr_intrastat_service/i18n/ca_ES.po
odoo_addons/l10n_fr_intrastat_service/i18n/cs.po
odoo_addons/l10n_fr_intrastat_service/i18n/da.po
odoo_addons/l10n_fr_intrastat_service/i18n/da_DK.po
odoo_addons/l10n_fr_intrastat_service/i18n/de.po
odoo_addons/l10n_fr_intrastat_service/i18n/el_GR.po
odoo_addons/l10n_fr_intrastat_service/i18n/en_GB.po
odoo_addons/l10n_fr_intrastat_service/i18n/es.po
odoo_addons/l10n_fr_intrastat_service/i18n/es_AR.po
odoo_addons/l10n_fr_intrastat_service/i18n/es_CL.po
odoo_addons/l10n_fr_intrastat_service/i18n/es_CO.po
odoo_addons/l10n_fr_intrastat_service/i18n/es_CR.po
odoo_addons/l10n_fr_intrastat_service/i18n/es_DO.po
odoo_addons/l10n_fr_intrastat_service/i18n/es_EC.po
odoo_addons/l10n_fr_intrastat_service/i18n/es_ES.po
odoo_addons/l10n_fr_intrastat_service/i18n/es_MX.po
odoo_addons/l10n_fr_intrastat_service/i18n/es_PE.po
odoo_addons/l10n_fr_intrastat_service/i18n/es_PY.po
odoo_addons/l10n_fr_intrastat_service/i18n/es_VE.po
odoo_addons/l10n_fr_intrastat_service/i18n/et.po
odoo_addons/l10n_fr_intrastat_service/i18n/eu.po
odoo_addons/l10n_fr_intrastat_service/i18n/fa.po
odoo_addons/l10n_fr_intrastat_service/i18n/fi.po
odoo_addons/l10n_fr_intrastat_service/i18n/fr.po
odoo8_addon_l10n_fr_intrastat_service-8.0.2.0.0.99.dev25.dist-info/METADATA
odoo8_addon_l10n_fr_intrastat_service-8.0.2.0.0.99.dev25.dist-info/WHEEL
odoo8_addon_l10n_fr_intrastat_service-8.0.2.0.0.99.dev25.dist-info/namespace_packages.txt
odoo8_addon_l10n_fr_intrastat_service-8.0.2.0.0.99.dev25.dist-info/top_level.txt
odoo8_addon_l10n_fr_intrastat_service-8.0.2.0.0.99.dev25.dist-info/RECORD
